thpham/lambda_layer_helmfile_v0/__init__.py
thpham/lambda_layer_helmfile_v0/py.typed
thpham/lambda_layer_helmfile_v0/_jsii/__init__.py
thpham/lambda_layer_helmfile_v0/_jsii/lambda-layer-helmfile-v0@2.0.2.jsii.tgz
thpham.lambda_layer_helmfile_v0-2.0.2.dist-info/LICENSE
thpham.lambda_layer_helmfile_v0-2.0.2.dist-info/METADATA
thpham.lambda_layer_helmfile_v0-2.0.2.dist-info/WHEEL
thpham.lambda_layer_helmfile_v0-2.0.2.dist-info/top_level.txt
thpham.lambda_layer_helmfile_v0-2.0.2.dist-info/RECORD
