Metadata-Version: 2.1
Name: thpham.lambda-layer-helmfile-v0
Version: 2.0.2
Summary: A Lambda Layer that contains Helmfile v0
Home-page: https://github.com/thpham/awscdk-asset-helmfile#readme
Author: thpham<224674+thpham@users.noreply.github.com>
License: Apache-2.0
Project-URL: Source, https://github.com/thpham/awscdk-asset-helmfile.git
Classifier: Intended Audience :: Developers
Classifier: Operating System :: OS Independent
Classifier: Programming Language :: JavaScript
Classifier: Programming Language :: Python :: 3 :: Only
Classifier: Programming Language :: Python :: 3.8
Classifier: Programming Language :: Python :: 3.9
Classifier: Programming Language :: Python :: 3.10
Classifier: Programming Language :: Python :: 3.11
Classifier: Typing :: Typed
Classifier: Development Status :: 5 - Production/Stable
Classifier: License :: OSI Approved
Requires-Python: ~=3.8
License-File: LICENSE
Requires-Dist: aws-cdk-lib <3.0.0,>=2.149.0
Requires-Dist: constructs <11.0.0,>=10.3.0
Requires-Dist: jsii <2.0.0,>=1.101.0
Requires-Dist: publication >=0.0.3
Requires-Dist: typeguard ~=2.13.3
